{
 "post_id": "2072408913920548946",
 "handle": "MitchDraws",
 "author_name": "@MitchDraws",
 "author_avatar": "https://abs.twimg.com/sticky/default_profile_images/default_profile_200x200.png",
 "url": "https://x.com/MitchDraws/status/2072408913920548946",
 "text": "I’m launching my OWN coin.\n\nNo insiders.\nNo other devs.\nNo one behind the scenes.\n\nCan’t believe what just happened, but lesson learned.",
 "photo": null,
 "stats": null,
 "posted_at": "2026-07-01T19:56:03.000Z",
 "saved_at": "2026-07-02T14:55:49.389Z",
 "post_missing_at_save": false,
 "receipt_page": "https://theretardedbull.xyz/receipt.html?id=2072408913920548946",
 "snapshot": "https://gazette-vault.theretardedbull.workers.dev/snapshot/2072408913920548946.svg",
 "pipeline_version": 6,
 "arweave_tx": "aILfEmAcMidZbxpFwceIxCjejEeLRxNdJ9L8AsJaTkg",
 "arweave": "https://arweave.net/aILfEmAcMidZbxpFwceIxCjejEeLRxNdJ9L8AsJaTkg",
 "arweave_gateway": "https://gazette-vault.theretardedbull.workers.dev/ar/aILfEmAcMidZbxpFwceIxCjejEeLRxNdJ9L8AsJaTkg",
 "arweave_deadline_height": 1951073,
 "arweave_block": 1950875,
 "arweave_bundle": "ehqIpUGvpiV3jNL_yGSnOCTw1JJC9gSSxQKuZmzys4Q"
}